dynamic_decimal/__init__.py
dynamic_decimal/db/__init__.py
dynamic_decimal/db/fields.py
dynamic_decimal/db/fields.py.bak
django_dynamic_decimal-0.3.0.dist-info/METADATA
django_dynamic_decimal-0.3.0.dist-info/WHEEL
django_dynamic_decimal-0.3.0.dist-info/top_level.txt
django_dynamic_decimal-0.3.0.dist-info/RECORD
